scsv/__init__.py
scsv/__main__.py
scsv/_version.py
scsv/scsv.py
scsv-0.1.6.dist-info/LICENSE
scsv-0.1.6.dist-info/METADATA
scsv-0.1.6.dist-info/WHEEL
scsv-0.1.6.dist-info/top_level.txt
scsv-0.1.6.dist-info/RECORD
