Metadata-Version: 2.2
Name: scsv
Version: 0.1.6
Summary: scsv - a simple csv reading tool
Author: SciWare LLC
Author-email: konung-yaropolk <yaropolk1995@gmail.com>
License:                                  Apache License
Project-URL: Homepage, https://github.com/konung-yaropolk/scsv
Project-URL: Repository, https://github.com/konung-yaropolk/scsv.git
Project-URL: Issues, https://github.com/konung-yaropolk/scsv/issues
Keywords: CSV,DSV,spreadsheets,Science,Statistics
Classifier: Programming Language :: Python
Classifier: Programming Language :: Python :: 3
Classifier: Programming Language :: Python :: 3.12
Classifier: License :: OSI Approved :: Apache Software License
Classifier: Operating System :: OS Independent
Classifier: Development Status :: 4 - Beta
Classifier: Intended Audience :: Developers
Classifier: Intended Audience :: Science/Research
Classifier: Natural Language :: English
Classifier: Topic :: Software Development :: Libraries
Classifier: Topic :: Software Development :: Libraries :: Python Modules
Classifier: Topic :: Text Processing :: Markup :: reStructuredText
Requires-Python: >=3.0
License-File: LICENSE
